tempest_zigzag/__init__.py
tempest_zigzag/cli.py
tempest_zigzag/tempest_junit_xml_suite.py
tempest_zigzag/tempest_test_list.py
tempest_zigzag/tempest_testcase_list.py
tempest_zigzag/tempest_testcase_xml.py
tempest_zigzag/tempest_zigzag.py
tempest_zigzag/data/tempest-zigzag-config.schema.json
tempest_zigzag/data/configs/example_tempest-zigzag_config.json
tempest_zigzag-0.1.0.dist-info/LICENSE
tempest_zigzag-0.1.0.dist-info/METADATA
tempest_zigzag-0.1.0.dist-info/WHEEL
tempest_zigzag-0.1.0.dist-info/entry_points.txt
tempest_zigzag-0.1.0.dist-info/top_level.txt
tempest_zigzag-0.1.0.dist-info/RECORD
