Metadata-Version: 2.1
Name: tempest-zigzag
Version: 0.1.0
Summary: Add new information to xml generated by tempest
Home-page: https://github.com/rcbops/tempest-zigzag
Author: rcbops
Author-email: rcb-deploy@lists.rackspace.com
Maintainer: rcbops
Maintainer-email: rcb-deploy@lists.rackspace.com
License: Apache Software License 2.0
Keywords: zigzag
Platform: UNKNOWN
Classifier: Development Status :: 4 - Beta
Classifier: Intended Audience :: Developers
Classifier: License :: OSI Approved :: Apache Software License
Classifier: Natural Language :: English
Classifier: Programming Language :: Python :: 2
Classifier: Programming Language :: Python :: 2.7
Classifier: Programming Language :: Python :: 3
Classifier: Programming Language :: Python :: 3.4
Classifier: Programming Language :: Python :: 3.5
Classifier: Programming Language :: Python :: 3.6
Classifier: Operating System :: OS Independent
Requires-Dist: Click (>=6.0)
Requires-Dist: lxml
Requires-Dist: future
Requires-Dist: jsonschema
Requires-Dist: rpc-zigzag (~=1.0)
